LICENSE
MANIFEST.in
README.rst
setup.py
data/archicow.conf.example
doc/Makefile
doc/conf.py
doc/config.rst
doc/index.rst
doc/install.rst
doc/process.rst
doc/scripts.rst
doc/storage.rst
prepscripts/README.rst
prepscripts/prepare_lvmsnap.sh
src/archicow/__init__.py
src/archicow/confparse.py
src/archicow/defs.py
src/archicow/sshagent.py
src/archicow/xenum.py
src/archicow.egg-info/PKG-INFO
src/archicow.egg-info/SOURCES.txt
src/archicow.egg-info/dependency_links.txt
src/archicow.egg-info/entry_points.txt
src/archicow.egg-info/requires.txt
src/archicow.egg-info/top_level.txt
src/archicow.egg-info/zip-safe
src/archicow/process/__init__.py
src/archicow/process/base.py
src/archicow/process/rsync.py
src/archicow/storage/__init__.py
src/archicow/storage/base.py
src/archicow/storage/btrfs.py
src/archicow/storage/hardlink.py
src/archicow/storage/simple.py