Metadata-Version: 1.1
Name: archicow
Version: 0.0.1.dev2
Summary: Backup system supporting copy-on-write storage.
Home-page: UNKNOWN
Author: Michal Belica
Author-email: devel@beli.sk
License: GPL-3
Keywords: backup
Platform: UNKNOWN
Classifier: Development Status :: 2 - Pre-Alpha
Classifier: Environment :: Console
Classifier: Intended Audience :: System Administrators
Classifier: License :: OSI Approved :: GNU General Public License v3 or later (GPLv3+)
Classifier: Operating System :: POSIX :: Linux
Classifier: Programming Language :: Python :: 3
Classifier: Topic :: System :: Archiving :: Backup
